diskcleaner/__init__.py
diskcleaner/cleaner.py
diskcleaner/main.py
diskcleaner-0.1.0a0.dist-info/METADATA
diskcleaner-0.1.0a0.dist-info/RECORD
diskcleaner-0.1.0a0.dist-info/WHEEL
diskcleaner-0.1.0a0.dist-info/entry_points.txt
diskcleaner-0.1.0a0.dist-info/top_level.txt
test/__init__.py
test/test_cleaner.py
